ldt_moneyball_client_staging/__init__.py
ldt_moneyball_client_staging/api_client.py
ldt_moneyball_client_staging/api_response.py
ldt_moneyball_client_staging/configuration.py
ldt_moneyball_client_staging/exceptions.py
ldt_moneyball_client_staging/py.typed
ldt_moneyball_client_staging/rest.py
ldt_moneyball_client_staging/api/__init__.py
ldt_moneyball_client_staging/api/companies_api.py
ldt_moneyball_client_staging/models/__init__.py
ldt_moneyball_client_staging/models/company.py
ldt_moneyball_client_staging/models/cp_alma_maters_response.py
ldt_moneyball_client_staging/models/cp_alma_maters_response_by_school_inner.py
ldt_moneyball_client_staging/models/cp_arr_dep_response.py
ldt_moneyball_client_staging/models/cp_arr_dep_response_by_dept_inner.py
ldt_moneyball_client_staging/models/cp_arr_dep_response_by_dept_inner_by_month_inner.py
ldt_moneyball_client_staging/models/cp_arr_dep_response_total.py
ldt_moneyball_client_staging/models/cp_arr_dep_response_total_by_month_inner.py
ldt_moneyball_client_staging/models/cp_depts_response.py
ldt_moneyball_client_staging/models/cp_depts_response_by_dept_inner.py
ldt_moneyball_client_staging/models/cp_emp_count_response.py
ldt_moneyball_client_staging/models/cp_emp_count_response_by_dept_inner.py
ldt_moneyball_client_staging/models/cp_emp_count_response_by_dept_inner_by_month_inner.py
ldt_moneyball_client_staging/models/cp_emp_count_response_by_level_inner.py
ldt_moneyball_client_staging/models/cp_emp_count_response_by_level_inner_by_month_inner.py
ldt_moneyball_client_staging/models/cp_emp_count_response_total.py
ldt_moneyball_client_staging/models/cp_emp_count_response_total_by_month_inner.py
ldt_moneyball_client_staging/models/cp_get_company_response.py
ldt_moneyball_client_staging/models/cp_prev_next_pct_response.py
ldt_moneyball_client_staging/models/cp_prev_next_pct_response_to_from_inner.py
ldt_moneyball_client_staging/models/cp_prev_next_pct_response_to_from_inner_group_values_inner.py
ldt_moneyball_client_staging-1.0.0.dist-info/METADATA
ldt_moneyball_client_staging-1.0.0.dist-info/WHEEL
ldt_moneyball_client_staging-1.0.0.dist-info/top_level.txt
ldt_moneyball_client_staging-1.0.0.dist-info/RECORD
