Metadata-Version: 2.2
Name: ldt-moneyball-client-staging
Version: 1.0.0
Summary: Moneyball
Home-page: 
Author: Live Data Support
Author-email: support@livedatatechnologies.com
Keywords: OpenAPI,OpenAPI-Generator,Moneyball
Requires-Dist: urllib3<3.0.0,>=1.25.3
Requires-Dist: python-dateutil>=2.8.2
Requires-Dist: pydantic>=2
Requires-Dist: typing-extensions>=4.7.1
Dynamic: author
Dynamic: author-email
Dynamic: description
Dynamic: description-content-type
Dynamic: keywords
Dynamic: requires-dist
Dynamic: summary
